photrack/__init__.py
photrack/__main__.py
photrack/main.py
photrack/test.py
photrack-0.1.2.dist-info/LICENSE
photrack-0.1.2.dist-info/METADATA
photrack-0.1.2.dist-info/WHEEL
photrack-0.1.2.dist-info/top_level.txt
photrack-0.1.2.dist-info/RECORD
